apimaticcalculatorpythonv3
tests
